{"_ts":[1514791769,1514878779],"_r":{"breakdown":{"html":{"bytes":[576,576],"requests":[1,1]},"js":{"bytes":[0,0],"requests":[0,0]},"css":{"bytes":[0,0],"requests":[0,0]},"image":{"bytes":[0,0],"requests":[0,0]},"flash":{"bytes":[0,0],"requests":[0,0]},"font":{"bytes":[0,0],"requests":[0,0]},"video":{"bytes":[0,0],"requests":[0,0]},"other":{"bytes":[0,0],"requests":[0,0]}},"date":[1514791769,1514878779],"domElements":[2,2],"domInteractive":[175,173],"firstPaint":[193,187],"fullyLoaded":[209,196],"id":["180101_PD_d11cab56b2c72eb6f991d437314300ed","180102_Z7_bdfad1b71ff3153b96b2ac230de33c02"],"loadTime":[150,149],"render":[0,0],"SpeedIndex":[0,0],"TTFB":[155,150],"videoFrames":[[{"_i":"ms_000000.jpg","_t":0,"_vc":100}],[{"_i":"ms_000000.jpg","_t":0,"_vc":100}]],"visualComplete":[0,0],"lighthouse":[45,45],"pagespeed":[100,100]}}